napari_feature_visualization/__init__.py
napari_feature_visualization/_sample_data.py
napari_feature_visualization/_version.py
napari_feature_visualization/feature_vis.py
napari_feature_visualization/napari.yaml
napari_feature_visualization/utils.py
napari_feature_visualization/_tests/__init__.py
napari_feature_visualization/_tests/test_feature_vis.py
napari_feature_visualization/_tests/test_sample_data.py
napari_feature_visualization-0.0.2.dist-info/licenses/LICENSE
napari_feature_visualization-0.0.2.dist-info/METADATA
napari_feature_visualization-0.0.2.dist-info/WHEEL
napari_feature_visualization-0.0.2.dist-info/entry_points.txt
napari_feature_visualization-0.0.2.dist-info/top_level.txt
napari_feature_visualization-0.0.2.dist-info/RECORD
