Metadata-Version: 2.4
Name: napari-feature-visualization
Version: 0.0.2
Summary: Visualizing feature measurements on label images in napari
Author: Joel Luethi, Adrian Tschan
Author-email: joel.luethi@uzh.ch
License: 
Project-URL: Bug Tracker, https://github.com/fractal-napari-plugins-collection/napari-feature-visualization/issues
Project-URL: Documentation, https://github.com/fractal-napari-plugins-collection/napari-feature-visualization#README.md
Project-URL: Source Code, https://github.com/fractal-napari-plugins-collection/napari-feature-visualization
Project-URL: User Support, https://github.com/fractal-napari-plugins-collection/napari-feature-visualization/issues
Classifier: Development Status :: 2 - Pre-Alpha
Classifier: Framework :: napari
Classifier: Intended Audience :: Developers
Classifier: License :: OSI Approved :: BSD License
Classifier: Operating System :: OS Independent
Classifier: Programming Language :: Python
Classifier: Programming Language :: Python :: 3
Classifier: Programming Language :: Python :: 3 :: Only
Classifier: Programming Language :: Python :: 3.9
Classifier: Programming Language :: Python :: 3.10
Classifier: Programming Language :: Python :: 3.11
Classifier: Programming Language :: Python :: 3.12
Classifier: Topic :: Scientific/Engineering :: Image Processing
Requires-Python: >=3.9
License-File: LICENSE
Requires-Dist: numpy
Requires-Dist: magicgui
Requires-Dist: qtpy
Requires-Dist: scikit-image
Requires-Dist: matplotlib
Requires-Dist: pandas
Requires-Dist: packaging
Provides-Extra: testing
Requires-Dist: tox; extra == "testing"
Requires-Dist: pytest; extra == "testing"
Requires-Dist: pytest-cov; extra == "testing"
Requires-Dist: pytest-qt; extra == "testing"
Requires-Dist: napari; extra == "testing"
Requires-Dist: pyqt5; extra == "testing"
Dynamic: license-file
